MANIFEST.in
README.md
setup.py
pyconclas/__init__.py
pyconclas/api.py
pyconclas.egg-info/PKG-INFO
pyconclas.egg-info/SOURCES.txt
pyconclas.egg-info/dependency_links.txt
pyconclas.egg-info/requires.txt
pyconclas.egg-info/top_level.txt
pyconclas/core/__init__.py
pyconclas/core/conclas_response.py
pyconclas/core/request.py
pyconclas/exceptions/__init__.py
pyconclas/exceptions/api_custom_exceptions.py
pyconclas/exceptions/client_exceptions.py
pyconclas/utils/__init__.py
pyconclas/utils/json_maker.py