Metadata-Version: 1.1
Name: pyconclas
Version: 0.1.1
Summary: The pyconclas is a client written in Python to use the service Conclas.
Home-page: https://github.com/s1mbi0se/conclas/tree/develop/conclas/clients/pyconclas
Author: Wil Filho
Author-email: will@simbioseventures.com
License: BSD
Keywords: conclas machine learning pyconclas
Platform: UNKNOWN
Classifier: Programming Language :: Python :: 2.7
Classifier: Topic :: Scientific/Engineering :: Information Analysis
Classifier: Topic :: Text Processing :: Linguistic
